{
  "test_id": "ecom_medium_004",
  "query": "Akun saya ter-hack dan ada transaksi mencurigakan, langkah apa yang harus dilakukan?",
  "category": "account",
  "difficulty": "medium",
  "expected_docs": [
    "troubleshooting_guide.md",
    "contact_escalation.md"
  ],
  "timestamp": "2025-10-24T14:02:55.868745",
  "rag_config": {
    "chunk_size": 500,
    "chunk_overlap": 50,
    "embedding_model": "BAAI/bge-m3",
    "embedding_type": "bge_m3_multifunctional",
    "vector_store": "BGE-M3 Custom",
    "retrieval_k": 3,
    "relevance_threshold": 0.3,
    "dense_weight": 0.4,
    "sparse_weight": 0.3,
    "colbert_weight": 0.3
  },
  "retrieval_trace": {
    "unique_docs": [
      "troubleshooting_guide.md",
      "contact_escalation.md",
      "product_faq.md"
    ],
    "num_chunks_retrieved": 3,
    "num_unique_docs": 3,
    "context_length_chars": 1220,
    "context_tokens_approx": 305,
    "retrieved_context_preview": "**Solusi:**\n1. Tunggu hingga 5 menit\n2. Cek folder spam untuk OTP email\n3. Pastikan nomor HP aktif dan ada sinyal\n4. Klik \"Kirim Ulang OTP\" (maksimal 3x)\n5. Ganti metode OTP (SMS ↔ Email)\n\n### Akun terkena hack/pembajakan\n**Gejala:** Ada transaksi mencurigakan, password berubah sendiri\n\n**Tindakan Cepat:**\n1. **SEGERA** hubungi CS via 1500-600\n2. Screenshot semua bukti aktivitas mencurigakan\n3. Ubah password email yang terhubung\n4. Aktifkan verifikasi 2 langkah setelah akun dipulihkan\n\n[Docs]\n\n#...",
    "latency_ms": 76.03
  },
  "evaluation": {
    "precision": 0.667,
    "recall": 1.0,
    "f1_score": 0.8,
    "reciprocal_rank": 1.0,
    "true_positives": [
      "troubleshooting_guide.md",
      "contact_escalation.md"
    ],
    "false_positives": [
      "product_faq.md"
    ],
    "false_negatives": []
  }
}